BLADE_Deconvolution/BLADE.py
BLADE_Deconvolution/BLADE_framework.py
BLADE_Deconvolution/BLADE_run.py
BLADE_Deconvolution/BLADE_wrapper.py
BLADE_Deconvolution/__init__.py
Deconvolution/BLADE.py
Deconvolution/Wrapper.py
Deconvolution/__init__.py
Deconvolution/framework.py
BLADE_Deconvolution-0.0.7.dist-info/LICENSE
BLADE_Deconvolution-0.0.7.dist-info/METADATA
BLADE_Deconvolution-0.0.7.dist-info/WHEEL
BLADE_Deconvolution-0.0.7.dist-info/top_level.txt
BLADE_Deconvolution-0.0.7.dist-info/RECORD
