Metadata-Version: 2.1
Name: BLADE-Deconvolution
Version: 0.0.7
Summary: BLADE (Bayesian Log-normAl DEconvolution)
Home-page: https://github.com/tgac-vumc/BLADE
Author: Yongsoo Kim
Author-email: anoyaro84@gmail.com
License: UNKNOWN
Platform: UNKNOWN
Classifier: Programming Language :: Python :: 3
Classifier: Programming Language :: Python :: 3.6
Classifier: Programming Language :: Python :: 3.7
Classifier: Programming Language :: Python :: 3.8
Classifier: License :: OSI Approved :: MIT License
Classifier: Operating System :: OS Independent
Requires-Python: >=3.6
Requires-Dist: numba
Requires-Dist: numpy
Requires-Dist: scipy
Requires-Dist: scikit-learn
Requires-Dist: joblib
